LICENSE
MANIFEST.in
README.rst
setup.py
django_easyregistration.egg-info/PKG-INFO
django_easyregistration.egg-info/SOURCES.txt
django_easyregistration.egg-info/dependency_links.txt
django_easyregistration.egg-info/top_level.txt
registration/__init__.py
registration/config.py
registration/forms.py
registration/urls.py
registration/views.py
registration/locale/es/LC_MESSAGES/django.mo
registration/locale/es/LC_MESSAGES/django.po
registration/static/registration/css/base.css
registration/static/registration/css/bootstrap-theme.min.css
registration/static/registration/css/bootstrap.min.css
registration/static/registration/js/bootstrap.min.js
registration/static/registration/js/jquery.min.js
registration/templates/registration/login.html
registration/templates/registration/register.html
registration/templates/registration/success.html