Metadata-Version: 1.1
Name: django-easyregistration
Version: 0.1
Summary: A simple Django app to manage users login/logout and registration.
Home-page: https://github.com/hcosta/django-easyregistration
Author: Hector Costa
Author-email: hcostaguzman@gmail.com
License: GPLv2
Platform: UNKNOWN
Classifier: Environment :: Web Environment
Classifier: Framework :: Django
Classifier: Intended Audience :: Developers
Classifier: License :: OSI Approved :: GNU General Public License v2 (GPLv2)
Classifier: Operating System :: OS Independent
Classifier: Programming Language :: Python
Classifier: Programming Language :: Python :: 2.6
Classifier: Programming Language :: Python :: 2.7
Classifier: Topic :: Internet :: WWW/HTTP
Classifier: Topic :: Internet :: WWW/HTTP :: Dynamic Content
